<?xml version="1.0" encoding="UTF-8"?><record_update>
    <sys_choice action="INSERT_OR_UPDATE" field="channel" table="x_1129732_wifi_man_wifi_incident" version="3">
        <sys_choice_set action="INSERT_OR_UPDATE">
            <element>channel</element>
            <name>x_1129732_wifi_man_wifi_incident</name>
            <sys_class_name>sys_choice_set</sys_class_name>
            <sys_created_by>admin</sys_created_by>
            <sys_created_on>2024-01-03 11:23:51</sys_created_on>
            <sys_mod_count>0</sys_mod_count>
            <sys_name>channel</sys_name>
            <sys_package display_value="wifi management system" source="x_1129732_wifi_man">ff4c099347173910eeeefb42e36d4313</sys_package>
            <sys_policy/>
            <sys_scope display_value="wifi management system">ff4c099347173910eeeefb42e36d4313</sys_scope>
            <sys_update_name>sys_choice_x_1129732_wifi_man_wifi_incident_channel</sys_update_name>
            <sys_updated_by>admin</sys_updated_by>
            <sys_updated_on>2024-01-03 11:23:51</sys_updated_on>
        </sys_choice_set>
        <sys_choice action="INSERT_OR_UPDATE">
            <dependent_value/>
            <element>channel</element>
            <hint/>
            <inactive>false</inactive>
            <label>Chat</label>
            <language>en</language>
            <name>x_1129732_wifi_man_wifi_incident</name>
            <sequence>0</sequence>
            <synonyms/>
            <sys_created_by>admin</sys_created_by>
            <sys_created_on>2024-01-03 11:23:51</sys_created_on>
            <sys_domain>global</sys_domain>
            <sys_domain_path>/</sys_domain_path>
            <sys_id>254cc805476bf110eeeefb42e36d439d</sys_id>
            <sys_mod_count>2</sys_mod_count>
            <sys_updated_by>admin</sys_updated_by>
            <sys_updated_on>2024-01-03 11:41:46</sys_updated_on>
            <value>chat</value>
        </sys_choice>
        <sys_choice action="INSERT_OR_UPDATE">
            <dependent_value/>
            <element>channel</element>
            <hint/>
            <inactive>false</inactive>
            <label>MAil</label>
            <language>en</language>
            <name>x_1129732_wifi_man_wifi_incident</name>
            <sequence>1</sequence>
            <synonyms/>
            <sys_created_by>admin</sys_created_by>
            <sys_created_on>2024-01-03 11:23:51</sys_created_on>
            <sys_domain>global</sys_domain>
            <sys_domain_path>/</sys_domain_path>
            <sys_id>354cc805476bf110eeeefb42e36d43a0</sys_id>
            <sys_mod_count>2</sys_mod_count>
            <sys_updated_by>admin</sys_updated_by>
            <sys_updated_on>2024-01-03 11:41:46</sys_updated_on>
            <value>mail</value>
        </sys_choice>
        <sys_choice action="INSERT_OR_UPDATE">
            <dependent_value/>
            <element>channel</element>
            <hint/>
            <inactive>false</inactive>
            <label>Portal</label>
            <language>en</language>
            <name>x_1129732_wifi_man_wifi_incident</name>
            <sequence>2</sequence>
            <synonyms/>
            <sys_created_by>admin</sys_created_by>
            <sys_created_on>2024-01-03 11:23:51</sys_created_on>
            <sys_domain>global</sys_domain>
            <sys_domain_path>/</sys_domain_path>
            <sys_id>f54cc805476bf110eeeefb42e36d43a2</sys_id>
            <sys_mod_count>2</sys_mod_count>
            <sys_updated_by>admin</sys_updated_by>
            <sys_updated_on>2024-01-03 11:41:46</sys_updated_on>
            <value>portal</value>
        </sys_choice>
        <sys_choice action="INSERT_OR_UPDATE">
            <dependent_value/>
            <element>channel</element>
            <hint/>
            <inactive>false</inactive>
            <label>Vertual Agent</label>
            <language>en</language>
            <name>x_1129732_wifi_man_wifi_incident</name>
            <sequence>3</sequence>
            <synonyms/>
            <sys_created_by>admin</sys_created_by>
            <sys_created_on>2024-01-03 11:23:51</sys_created_on>
            <sys_domain>global</sys_domain>
            <sys_domain_path>/</sys_domain_path>
            <sys_id>b94cc805476bf110eeeefb42e36d43a4</sys_id>
            <sys_mod_count>2</sys_mod_count>
            <sys_updated_by>admin</sys_updated_by>
            <sys_updated_on>2024-01-03 11:41:46</sys_updated_on>
            <value>vertual_agent</value>
        </sys_choice>
    </sys_choice>
</record_update>
